ezrpg/__init__.py
ezrpg/character.py
ezrpg/sheet.py
ezrpg/tests/__init__.py
ezrpg/tests/test_character.py
ezrpg/tests/test_init.py
ezrpg/tests/test_sheet.py
ezrpg-2022.9.26.13826.dist-info/METADATA
ezrpg-2022.9.26.13826.dist-info/WHEEL
ezrpg-2022.9.26.13826.dist-info/top_level.txt
ezrpg-2022.9.26.13826.dist-info/RECORD
